{
  "parent": "electrofynamic_thaumatury:normal/energy_maker",
  "criteria": {
    "has_energy_antenna_0": {
      "conditions": {
        "items": [
          {
            "items": "electrofynamic_thaumatury:energy_transmission_antenna"
          }
        ]
      },
      "trigger": "minecraft:inventory_changed"
    }
  },
  "display": {
    "description": {
      "translate": "advancements.electrofynamic_thaumatury.energy_send.description"
    },
    "icon": {
      "count": 1,
      "id": "electrofynamic_thaumatury:energy_transmission_antenna"
    },
    "title": {
      "translate": "advancements.electrofynamic_thaumatury.energy_send.title"
    }
  },
  "requirements": [
    [
      "has_energy_antenna_0"
    ]
  ],
  "sends_telemetry_event": true
}